layabout.py
layabout-1.0.2.dist-info/AUTHORS.rst
layabout-1.0.2.dist-info/LICENSE
layabout-1.0.2.dist-info/METADATA
layabout-1.0.2.dist-info/WHEEL
layabout-1.0.2.dist-info/top_level.txt
layabout-1.0.2.dist-info/RECORD
