Metadata-Version: 2.1
Name: layabout
Version: 1.0.2
Summary: A small event handling library on top of the Slack RTM API.
Home-page: https://github.com/reillysiemens/layabout
Author: Reilly Tucker Siemens
Author-email: reilly@tuckersiemens.com
License: ISCL
Keywords: Slack RTM API Bot Framework
Platform: UNKNOWN
Classifier: Development Status :: 5 - Production/Stable
Classifier: Environment :: Console
Classifier: Intended Audience :: Developers
Classifier: License :: OSI Approved :: ISC License (ISCL)
Classifier: Natural Language :: English
Classifier: Operating System :: POSIX :: Linux
Classifier: Operating System :: POSIX :: BSD :: FreeBSD
Classifier: Programming Language :: Python :: 3.6
Classifier: Programming Language :: Python :: 3.7
Classifier: Programming Language :: Python :: 3.8
Classifier: Programming Language :: Python :: 3 :: Only
Classifier: Programming Language :: Python :: Implementation :: CPython
Classifier: Topic :: Communications :: Chat
Classifier: Topic :: Software Development :: Libraries
Requires-Python: >=3.6
Requires-Dist: slackclient (~=1.2)
Provides-Extra: dev
Requires-Dist: flake8 (~=3.7.8) ; extra == 'dev'
Requires-Dist: mypy (~=0.740.0) ; extra == 'dev'
Requires-Dist: pytest (~=5.2) ; extra == 'dev'
Requires-Dist: pytest-cov (~=2.8) ; extra == 'dev'
Requires-Dist: Sphinx (~=2.2) ; extra == 'dev'
Requires-Dist: sphinx-autodoc-typehints (~=1.8) ; extra == 'dev'
Provides-Extra: docs
Requires-Dist: Sphinx (~=2.2) ; extra == 'docs'
Requires-Dist: sphinx-autodoc-typehints (~=1.8) ; extra == 'docs'
Provides-Extra: test
Requires-Dist: flake8 (~=3.7.8) ; extra == 'test'
Requires-Dist: mypy (~=0.740.0) ; extra == 'test'
Requires-Dist: pytest (~=5.2) ; extra == 'test'
Requires-Dist: pytest-cov (~=2.8) ; extra == 'test'
